{
    "name": "Array Dimensions",
    "prev": "Array Indices",
    "next": "Implementation Limits on Individual Array Dimensions",
    "up": "Array Elements",
    "header": {
        "type": null,
        "text": null
    },
    "sections": [
        {
            "type": "",
            "text": ""
        },
        {
            "type": "Array Dimensions",
            "text": "An axis of an array is called a dimension .\nEach dimension is a non-negative\nfixnum;\nif any dimension of an array is zero, the array has no elements.  It is\npermissible for a dimension to be zero, in which case the array has no\nelements, and any attempt to access an element is an error.  However,\nother properties of the array, such as the dimensions themselves, may be\nused.\n"
        }
    ],
    "_otext": "File: gcl.info,  Node: Array Dimensions,  Next: Implementation Limits on Individual Array Dimensions,  Prev: Array Indices,  Up: Array Elements\n\nArray Dimensions\n................\n\nAn axis of an array is called a dimension .\n\nEach dimension is a non-negative\n\nfixnum;\n\nif any dimension of an array is zero, the array has no elements.  It is\npermissible for a dimension to be zero, in which case the array has no\nelements, and any attempt to access an element is an error.  However,\nother properties of the array, such as the dimensions themselves, may be\nused.\n\n"
}