{
    "name": "Defining Classes",
    "prev": "Introduction to Classes",
    "next": "Creating Instances of Classes",
    "up": "Classes",
    "header": {
        "type": null,
        "text": "Defining Classes"
    },
    "sections": [
        {
            "type": "",
            "text": "The macro defclass is used to define a new named class.\nThe definition of a class includes:\n*\n     The name of the new class.  For newly-defined classes this name is a\n     proper name.\n*\n     The list of the direct superclasses of the new class.\n*\n     A set of slot specifiers .  Each slot specifier includes the name of\n     the slot and zero or more slot options.  A slot option pertains only\n     to a single slot.  If a class definition contains two slot specifiers\n     with the same name, an error is signaled.\n*\n     A set of class options.  Each class option pertains to the class as a\n     whole.\nThe slot options and class options of the defclass form provide mechanisms\nfor the following:\n*\n     Supplying a default initial value form for a given slot.\n*\n     Requesting that methods for generic functions be automatically\n     generated for reading or writing slots.\n*\n     Controlling whether a given slot is shared by all instances of the\n     class or whether each instance of the class has its own slot.\n*\n     Supplying a set of initialization arguments and initialization\n     argument defaults to be used in instance creation.\n*\n     Indicating that the metaclass is to be other than the default.  The\n     :metaclass option is reserved for future use; an implementation can\n     be extended to make use of the :metaclass option.\n*\n     Indicating the expected type for the value stored in the slot.\n*\n     Indicating the documentation string for the slot.\n"
        }
    ],
    "_otext": "File: gcl.info,  Node: Defining Classes,  Next: Creating Instances of Classes,  Prev: Introduction to Classes,  Up: Classes\n\nDefining Classes\n----------------\n\nThe macro defclass is used to define a new named class.\n\nThe definition of a class includes:\n\n*\n     The name of the new class.  For newly-defined classes this name is a\n     proper name.\n\n*\n     The list of the direct superclasses of the new class.\n\n*\n     A set of slot specifiers .  Each slot specifier includes the name of\n     the slot and zero or more slot options.  A slot option pertains only\n     to a single slot.  If a class definition contains two slot specifiers\n     with the same name, an error is signaled.\n\n*\n     A set of class options.  Each class option pertains to the class as a\n     whole.\n\nThe slot options and class options of the defclass form provide mechanisms\nfor the following:\n\n*\n     Supplying a default initial value form for a given slot.\n\n*\n     Requesting that methods for generic functions be automatically\n     generated for reading or writing slots.\n\n*\n     Controlling whether a given slot is shared by all instances of the\n     class or whether each instance of the class has its own slot.\n\n*\n     Supplying a set of initialization arguments and initialization\n     argument defaults to be used in instance creation.\n\n*\n     Indicating that the metaclass is to be other than the default.  The\n     :metaclass option is reserved for future use; an implementation can\n     be extended to make use of the :metaclass option.\n\n*\n     Indicating the expected type for the value stored in the slot.\n\n*\n     Indicating the documentation string for the slot.\n\n"
}