{
    "name": "Deftype Lambda Lists",
    "prev": "Defsetf Lambda Lists",
    "next": "Define-modify-macro Lambda Lists",
    "up": "Lambda Lists",
    "header": {
        "type": null,
        "text": "Deftype Lambda Lists"
    },
    "sections": [
        {
            "type": "",
            "text": "A deftype lambda list is used by deftype.\nA deftype lambda list has the same syntax as a macro lambda list, and can\ntherefore contain the lambda list keywords as a macro lambda list.\nA deftype lambda list differs from a macro lambda list only in that if no\ninit-form is supplied for an optional parameter or keyword parameter in\nthe lambda-list, the default value for that parameter is the symbol *\n(rather than nil).\n"
        }
    ],
    "_otext": "File: gcl.info,  Node: Deftype Lambda Lists,  Next: Define-modify-macro Lambda Lists,  Prev: Defsetf Lambda Lists,  Up: Lambda Lists\n\nDeftype Lambda Lists\n--------------------\n\nA deftype lambda list is used by deftype.\n\nA deftype lambda list has the same syntax as a macro lambda list, and can\ntherefore contain the lambda list keywords as a macro lambda list.\n\nA deftype lambda list differs from a macro lambda list only in that if no\ninit-form is supplied for an optional parameter or keyword parameter in\nthe lambda-list, the default value for that parameter is the symbol *\n(rather than nil).\n\n"
}