{
    "name": "Determining the Effective Method",
    "prev": "Method Selection and Combination",
    "next": "Selecting the Applicable Methods",
    "up": "Method Selection and Combination",
    "header": {
        "type": null,
        "text": null
    },
    "sections": [
        {
            "type": "",
            "text": ""
        },
        {
            "type": "Determining the Effective Method",
            "text": "The effective method is determined by the following three-step procedure:\n1.\n     Select the applicable methods.\n2.\n     Sort the applicable methods by precedence order, putting the most\n     specific method first.\n3.\n     Apply method combination to the sorted list of applicable methods,\n     producing the effective method.\n"
        }
    ],
    "_otext": "File: gcl.info,  Node: Determining the Effective Method,  Next: Selecting the Applicable Methods,  Prev: Method Selection and Combination,  Up: Method Selection and Combination\n\nDetermining the Effective Method\n................................\n\nThe effective method is determined by the following three-step procedure:\n\n1.\n     Select the applicable methods.\n\n2.\n     Sort the applicable methods by precedence order, putting the most\n     specific method first.\n\n3.\n     Apply method combination to the sorted list of applicable methods,\n     producing the effective method.\n\n"
}