{
    "name": "Filenames",
    "prev": "Hash Tables",
    "next": "Files",
    "up": "Top",
    "header": {
        "type": null,
        "text": "Filenames"
    },
    "sections": [
        {
            "type": "",
            "text": "* Menu:\n* Overview of Filenames::\n* Pathnames::\n* Logical Pathnames::\n* Filenames Dictionary::\n"
        }
    ],
    "_otext": "File: gcl.info,  Node: Filenames,  Next: Files,  Prev: Hash Tables,  Up: Top\n\nFilenames\n*********\n\n* Menu:\n\n* Overview of Filenames::\n* Pathnames::\n* Logical Pathnames::\n* Filenames Dictionary::\n\n"
}