{
    "name": "Resolution of Apparent Conflicts in Exceptional Situations",
    "prev": "Treatment of Exceptional Situations",
    "next": "Examples of Resolution of Apparent Conflict in Exceptional Situations",
    "up": "Conforming Implementations",
    "header": {
        "type": null,
        "text": null
    },
    "sections": [
        {
            "type": "",
            "text": ""
        },
        {
            "type": "Resolution of Apparent Conflicts in Exceptional Situations",
            "text": "If more than one passage in this specification appears to apply to the\nsame situation but in conflicting ways, the passage that appears to\ndescribe the situation in the most specific way (not necessarily the\npassage that provides the most constrained kind of error detection) takes\nprecedence.\n"
        }
    ],
    "_otext": "File: gcl.info,  Node: Resolution of Apparent Conflicts in Exceptional Situations,  Next: Examples of Resolution of Apparent Conflict in Exceptional Situations,  Prev: Treatment of Exceptional Situations,  Up: Conforming Implementations\n\nResolution of Apparent Conflicts in Exceptional Situations\n..........................................................\n\nIf more than one passage in this specification appears to apply to the\nsame situation but in conflicting ways, the passage that appears to\ndescribe the situation in the most specific way (not necessarily the\npassage that provides the most constrained kind of error detection) takes\nprecedence.\n\n"
}