{
    "name": "Syntax of an Integer",
    "prev": "Syntax of a Rational",
    "next": "Syntax of a Ratio",
    "up": "Constructing Numbers from Tokens",
    "header": {
        "type": null,
        "text": null
    },
    "sections": [
        {
            "type": "",
            "text": ""
        },
        {
            "type": "Syntax of an Integer",
            "text": "Integers can be written as a sequence of digits, optionally preceded by a\nsign and optionally followed by a decimal point; see Figure~2-9.  When a\ndecimal point is used, the digits are taken to be in radix 10; when no\ndecimal point is used, the digits are taken to be in radix given by the\ncurrent input base.\nFor information on how integers are printed, see *Note Printing Integers::.\n"
        }
    ],
    "_otext": "File: gcl.info,  Node: Syntax of an Integer,  Next: Syntax of a Ratio,  Prev: Syntax of a Rational,  Up: Constructing Numbers from Tokens\n\nSyntax of an Integer\n....................\n\nIntegers can be written as a sequence of digits, optionally preceded by a\nsign and optionally followed by a decimal point; see Figure~2-9.  When a\ndecimal point is used, the digits are taken to be in radix 10; when no\ndecimal point is used, the digits are taken to be in radix given by the\ncurrent input base.\n\nFor information on how integers are printed, see *Note Printing Integers::.\n\n"
}